src/__init__.py
src/next_api_starter/__init__.py
src/next_api_starter/create_nextapi.py
src/next_api_starter/main.py
src/next_api_starter/update_nextapi.py
src/next_api_starter/template/__init__.py
next_api_starter-0.1.4.dist-info/LICENSE.txt
next_api_starter-0.1.4.dist-info/METADATA
next_api_starter-0.1.4.dist-info/WHEEL
next_api_starter-0.1.4.dist-info/entry_points.txt
next_api_starter-0.1.4.dist-info/top_level.txt
next_api_starter-0.1.4.dist-info/RECORD
