Metadata-Version: 2.1
Name: next-api-starter
Version: 0.1.4
Summary: Starter template for Next.js and FastAPI projects
License-File: LICENSE.txt
Requires-Dist: uvicorn[standard]
